{
  "channels": [
    {}
  ],
  "programs": [
    {
      "start": "2026-05-04T20:10:00+05:00",
      "stop": "2026-05-04T21:00:00+05:00",
      "title": "Harry's Practice",
      "desc": "Join Dr Harry Cooper and Dr Katrina Warren for everything you need to know about animals.",
      "language": "en",
      "rating": "G",
      "categories": [
        "Special Interest"
      ],
      "episode": "E107",
      "icon": "https://www.fetchtv.com.au/v2/epg/program/132203/image/334x188"
    },
    {
      "start": "2026-05-04T21:00:00+05:00",
      "stop": "2026-05-04T21:30:00+05:00",
      "title": "Home Shopping",
      "sub_title": "Belena Air Stretch (A2830BMM08DOA)",
      "desc": "Shopping program.",
      "language": "en",
      "rating": "G",
      "categories": [
        "Special Interest"
      ],
      "episode": "S1 E269",
      "icon": "https://www.fetchtv.com.au/v2/epg/program/234200/image/334x188"
    },
    {
      "start": "2026-05-04T21:30:00+05:00",
      "stop": "2026-05-04T22:00:00+05:00",
      "title": "Home Shopping",
      "sub_title": "Dr Hos MotionCiser (DRMC2830B27904)",
      "desc": "Shopping program.",
      "language": "en",
      "rating": "G",
      "categories": [
        "Special Interest"
      ],
      "episode": "S1 E121",
      "icon": "https://www.fetchtv.com.au/v2/epg/program/234200/image/334x188"
    },
    {
      "start": "2026-05-04T22:00:00+05:00",
      "stop": "2026-05-04T22:30:00+05:00",
      "title": "Home Shopping",
      "sub_title": "Pocket Hose Copper Head (PHCH2830A17",
      "desc": "Shopping program.",
      "language": "en",
      "rating": "G",
      "categories": [
        "Special Interest"
      ],
      "episode": "S1 E130",
      "icon": "https://www.fetchtv.com.au/v2/epg/program/234200/image/334x188"
    },
    {
      "start": "2026-05-04T22:30:00+05:00",
      "stop": "2026-05-04T23:00:00+05:00",
      "title": "Home Shopping",
      "sub_title": "Kelton Cookware (A2830KCW02QRA)",
      "desc": "Shopping program.",
      "language": "en",
      "rating": "G",
      "categories": [
        "Special Interest"
      ],
      "episode": "S1 E246",
      "icon": "https://www.fetchtv.com.au/v2/epg/program/234200/image/334x188"
    },
    {
      "start": "2026-05-04T23:00:00+05:00",
      "stop": "2026-05-05T00:00:00+05:00",
      "title": "NBC Today",
      "desc": "International news and weather including interviews with newsmakers in the world of politics, business, media, entertainment and sport.",
      "language": "en",
      "rating": "NR",
      "categories": [
        "News"
      ],
      "episode": "S26 E124",
      "icon": "https://www.fetchtv.com.au/v2/epg/program/132440/image/334x188"
    }
  ]
}