{
  "channels": [
    {}
  ],
  "programs": [
    {
      "start": "2026-05-07T05:52:43+05:00",
      "stop": "2026-05-07T05:52:44+05:00",
      "title": "Food Show",
      "desc": "BBC Food provides cooking shows, recipe-based entertainment, and culinary programming featuring top British chefs. It showcases traditional and modern cuisine with easy-to-follow food inspiration and kitchen techniques. The channel focuses on lifestyle cooking content, travel-inspired dishes, and everyday home cooking ideas.",
      "language": "en",
      "categories": [
        "Lifestyle"
      ]
    },
    {
      "start": "2026-05-07T05:52:44+05:00",
      "stop": "2026-05-07T06:24:45+05:00",
      "title": "The Naked Chef",
      "sub_title": "Rock and Roast",
      "desc": "Jamie prepares roast beef, Yorkshire puddings and baked onions.",
      "language": "en",
      "rating": "G",
      "categories": [
        "BBC"
      ],
      "episode": "S03E02"
    },
    {
      "start": "2026-05-07T06:24:45+05:00",
      "stop": "2026-05-07T06:56:51+05:00",
      "title": "The Naked Chef",
      "sub_title": "Godfather",
      "desc": "BBC Food provides cooking shows, recipe-based entertainment, and culinary programming featuring top British chefs. It showcases traditional and modern cuisine with easy-to-follow food inspiration and kitchen techniques. The channel focuses on lifestyle cooking content, travel-inspired dishes, and everyday home cooking ideas.",
      "language": "en",
      "rating": "G",
      "categories": [
        "BBC"
      ],
      "episode": "S03E03"
    },
    {
      "start": "2026-05-07T06:56:51+05:00",
      "stop": "2026-05-07T07:56:51+05:00",
      "title": "Food Show",
      "desc": "BBC Food provides cooking shows, recipe-based entertainment, and culinary programming featuring top British chefs. It showcases traditional and modern cuisine with easy-to-follow food inspiration and kitchen techniques. The channel focuses on lifestyle cooking content, travel-inspired dishes, and everyday home cooking ideas.",
      "language": "en",
      "categories": [
        "Lifestyle"
      ]
    },
    {
      "start": "2026-05-07T07:56:51+05:00",
      "stop": "2026-05-07T08:56:51+05:00",
      "title": "Food Show",
      "desc": "BBC Food provides cooking shows, recipe-based entertainment, and culinary programming featuring top British chefs. It showcases traditional and modern cuisine with easy-to-follow food inspiration and kitchen techniques. The channel focuses on lifestyle cooking content, travel-inspired dishes, and everyday home cooking ideas.",
      "language": "en",
      "categories": [
        "Lifestyle"
      ]
    },
    {
      "start": "2026-05-07T08:56:51+05:00",
      "stop": "2026-05-07T09:56:51+05:00",
      "title": "Food Show",
      "desc": "BBC Food provides cooking shows, recipe-based entertainment, and culinary programming featuring top British chefs. It showcases traditional and modern cuisine with easy-to-follow food inspiration and kitchen techniques. The channel focuses on lifestyle cooking content, travel-inspired dishes, and everyday home cooking ideas.",
      "language": "en",
      "categories": [
        "Lifestyle"
      ]
    }
  ]
}