{
  "channels": [
    {}
  ],
  "programs": [
    {
      "start": "2026-05-06T23:30:00+05:00",
      "stop": "2026-05-07T00:00:00+05:00",
      "title": "EastEnders",
      "desc": "Ian instantly regrets his actions, Grant steps in to help a friend, and Gina and Harry are forced to come clean.",
      "language": "en",
      "categories": [
        "Entertainment",
        "Soap"
      ],
      "icon": "https://images.metadata.sky.com/pd-image/07d63342-515a-4283-8e2b-8d0c88e64527/16-9"
    },
    {
      "start": "2026-05-07T00:00:00+05:00",
      "stop": "2026-05-07T01:00:00+05:00",
      "title": "The Repair Shop",
      "desc": "The team revive a cherished rocking horse, a spectacular set of conga drums, and a logbook that played a key role in British LGBTQ+ history.",
      "language": "en",
      "categories": [
        "Entertainment",
        "Antiques"
      ],
      "icon": "https://images.metadata.sky.com/pd-image/ef92bf69-c211-4677-9b61-570401cf99eb/16-9"
    },
    {
      "start": "2026-05-07T01:00:00+05:00",
      "stop": "2026-05-07T01:30:00+05:00",
      "title": "Amandaland",
      "desc": "Amanda uses a school careers talk to prove she's not shallow. Contains some strong language.",
      "language": "en",
      "categories": [
        "Entertainment",
        "Comedy"
      ],
      "icon": "https://images.metadata.sky.com/pd-image/e8a0917b-aa5d-400b-872e-69656cf8800f/16-9"
    },
    {
      "start": "2026-05-07T01:30:00+05:00",
      "stop": "2026-05-07T02:00:00+05:00",
      "title": "Only Child",
      "desc": "Richard just wants to hide away from the world, but Ken has other ideas - mainly forcing him to join the protest group fighting to save the local allotments.",
      "language": "en",
      "categories": [
        "Entertainment",
        "Comedy"
      ],
      "icon": "https://images.metadata.sky.com/pd-image/17b674e4-2483-4ae0-93d3-6debad4aa908/16-9"
    },
    {
      "start": "2026-05-07T02:00:00+05:00",
      "stop": "2026-05-07T02:30:00+05:00",
      "title": "BBC News and Weather",
      "desc": "The latest national and international news, with reports from BBC correspondents worldwide.",
      "language": "en",
      "categories": [
        "News & Documentary",
        "News"
      ],
      "icon": "https://images.metadata.sky.com/pd-image/55377f4e-a0b3-4d68-82b1-3d1657e478b2/16-9"
    },
    {
      "start": "2026-05-07T02:30:00+05:00",
      "stop": "2026-05-07T02:40:00+05:00",
      "title": "BBC London News",
      "desc": "The latest news, sport and weather from London.",
      "language": "en",
      "categories": [
        "News & Documentary",
        "News"
      ],
      "icon": "https://images.metadata.sky.com/pd-image/5b94e694-e5a4-4257-864b-d997544fd963/16-9"
    }
  ]
}