{
  "channels": [
    {}
  ],
  "programs": [
    {
      "start": "2026-05-06T07:00:00+05:00",
      "stop": "2026-05-06T08:00:00+05:00",
      "title": "CNA Correspondent",
      "desc": "They're your eyes and ears around the globe. CNA's network of correspondents shines a light on stories from their corners of the world, from groundbreaking events to up-and-coming trends.",
      "language": "en"
    },
    {
      "start": "2026-05-06T08:00:00+05:00",
      "stop": "2026-05-06T10:00:00+05:00",
      "title": "Asia Now",
      "desc": "(Live) Non-stop breaking stories, expert analysis and extensive news coverage every hour.",
      "language": "en"
    },
    {
      "start": "2026-05-06T10:00:00+05:00",
      "stop": "2026-05-06T11:00:00+05:00",
      "title": "When Titans Clash S12: China And The Iran War",
      "desc": "How is the Iran crisis impacting China's energy policies, its clean energy exports and nuclear power plans? With US approval ratings dropping globally, what does it mean for China-ASEAN, and China-Europe relations?",
      "language": "en"
    },
    {
      "start": "2026-05-06T11:00:00+05:00",
      "stop": "2026-05-06T13:00:00+05:00",
      "title": "Asia Now",
      "desc": "(Live) Non-stop breaking stories, expert analysis and extensive news coverage every hour.",
      "language": "en"
    },
    {
      "start": "2026-05-06T13:00:00+05:00",
      "stop": "2026-05-06T14:00:00+05:00",
      "title": "Insight 2026/2027",
      "desc": "Business Process Outsourcing is one of the industries most likely to be disrupted by AI. India and Philippines have the world's largest BPO sectors. Will tech threaten the livelihoods of millions?",
      "language": "en"
    },
    {
      "start": "2026-05-06T14:00:00+05:00",
      "stop": "2026-05-06T14:02:00+05:00",
      "title": "Headline News",
      "desc": "(Live) The latest top stories of the hour.",
      "language": "en"
    }
  ]
}