{
  "channels": [
    {}
  ],
  "programs": [
    {
      "start": "2026-05-05T01:11:00+05:00",
      "stop": "2026-05-05T02:01:00+05:00",
      "title": "Eva Longoria: Searching for Mexico",
      "desc": "Longoria discovers the hidden magic of Oaxaca that boasts some of the finest ingredients in Mexico.",
      "language": "en",
      "episode": "S01E03",
      "icon": "https://images.sr.roku.com/idType/roku-trc/context/trc/id/3815cb7ca79654a9b8824a89480590c9/images/gracenote/assets/p22303734_b_h10_aa.jpg"
    },
    {
      "start": "2026-05-05T02:01:00+05:00",
      "stop": "2026-05-05T02:51:00+05:00",
      "title": "Eva Longoria: Searching for Mexico",
      "desc": "Eva Longoria visits the northeastern state of Nuevo Le\u00f3n, bordering her home state of Texas. As little grows there, and with meat on every menu, inventive and resourceful chefs transform simple ingredients into culinary delights.",
      "language": "en",
      "episode": "S01E04",
      "icon": "https://images.sr.roku.com/idType/roku-trc/context/trc/id/3815cb7ca79654a9b8824a89480590c9/images/gracenote/assets/p22303734_b_h10_aa.jpg"
    },
    {
      "start": "2026-05-05T02:51:00+05:00",
      "stop": "2026-05-05T03:41:00+05:00",
      "title": "Eva Longoria: Searching for Mexico",
      "desc": "Eva visits the state of Jalisco, where much of what is seen is quintessentially Mexican originated.",
      "language": "en",
      "episode": "S01E05",
      "icon": "https://images.sr.roku.com/idType/roku-trc/context/trc/id/3815cb7ca79654a9b8824a89480590c9/images/gracenote/assets/p22303734_b_h10_aa.jpg"
    },
    {
      "start": "2026-05-05T03:41:00+05:00",
      "stop": "2026-05-05T04:31:00+05:00",
      "title": "Eva Longoria: Searching for Mexico",
      "desc": "Eva Longoria explores Veracruz, the port gateway between Mexico and the rest of the world.",
      "language": "en",
      "episode": "S01E06",
      "icon": "https://images.sr.roku.com/idType/roku-trc/context/trc/id/3815cb7ca79654a9b8824a89480590c9/images/gracenote/assets/p22303734_b_h10_aa.jpg"
    },
    {
      "start": "2026-05-05T04:31:00+05:00",
      "stop": "2026-05-05T04:52:00+05:00",
      "title": "Forensic Files II",
      "desc": "A woman is found murdered on the side of a driveway; it would remain unsolved for three decades.",
      "language": "en",
      "episode": "S02E15",
      "icon": "https://images.sr.roku.com/idType/roku-trc/context/trc/id/68b37740ce725582b53c9820f6cb0492/images/gracenote/assets/p17847753_b_h8_an.jpg"
    },
    {
      "start": "2026-05-05T04:52:00+05:00",
      "stop": "2026-05-05T05:13:00+05:00",
      "title": "Forensic Files II",
      "desc": "When a doctor dies in a house fire, an arson investigation leads to the son of the doctor's nurse.",
      "language": "en",
      "episode": "S02E11",
      "icon": "https://images.sr.roku.com/idType/roku-trc/context/trc/id/68b37740ce725582b53c9820f6cb0492/images/gracenote/assets/p17847753_b_h8_an.jpg"
    }
  ]
}