{
  "channels": [
    {}
  ],
  "programs": [
    {
      "start": "2026-05-05T06:00:00+05:00",
      "stop": "2026-05-05T09:00:00+05:00",
      "title": "The Godfather",
      "desc": "Widely regarded as one of the greatest films of all time, this mob drama, based on Mario Puzo's novel of the same name, focuses on the powerful Italian-American crime family of Don Vito Corleone (Marlon Brando). When the don's youngest son, Michael (Al Pacino), reluctantly joins the Mafia, he becomes involved in the inevitable cycle of violence and betrayal. Although Michael tries to maintain a normal relationship with his wife, Kay (Diane Keaton), he is drawn deeper into the family business.",
      "date": "1972",
      "language": "en",
      "rating": "R",
      "categories": [
        "Movie",
        "Crime drama"
      ],
      "icon": "http://dtil.tmsimg.com/assets/p6326_v_h8_be.jpg?w=960&h=540",
      "credits": {
        "director": [
          "Francis Ford Coppola"
        ],
        "actor": [
          "Marlon Brando",
          "Al Pacino",
          "James Caan"
        ]
      }
    },
    {
      "start": "2026-05-05T09:00:00+05:00",
      "stop": "2026-05-05T12:25:00+05:00",
      "title": "The Godfather, Part II",
      "desc": "The compelling sequel to \"The Godfather,\" contrasting the life of Corleone father and son. Traces the problems of Michael Corleone (Al Pacino) in 1958 and that of a young immigrant Vito Corleone (Robert De Niro) in 1917's Hell's Kitchen. Michael survives many misfortunes and Vito is introduced to a life of crime.",
      "date": "1974",
      "language": "en",
      "rating": "R",
      "categories": [
        "Movie",
        "Crime drama"
      ],
      "icon": "http://dtil.tmsimg.com/assets/p6319_v_h8_bi.jpg?w=960&h=540",
      "credits": {
        "director": [
          "Francis Ford Coppola"
        ],
        "actor": [
          "Al Pacino",
          "Robert Duvall",
          "Diane Keaton"
        ]
      }
    },
    {
      "start": "2026-05-05T12:25:00+05:00",
      "stop": "2026-05-05T13:55:00+05:00",
      "title": "Soccer Mom Madam",
      "desc": "A single mother establishes a high-end escort service that matches beautiful young women with the wealthiest and most powerful men in the city. She manages to keep her lifestyle hidden from her kids and others until the FBI starts to investigate her.",
      "date": "2021",
      "language": "en",
      "rating": "A14",
      "categories": [
        "Movie",
        "Docudrama"
      ],
      "icon": "http://dtil.tmsimg.com/assets/p19797794_v_h8_ae.jpg?w=960&h=540",
      "credits": {
        "director": [
          "Kevin Fair"
        ],
        "actor": [
          "Jana Kramer"
        ]
      }
    },
    {
      "start": "2026-05-05T13:55:00+05:00",
      "stop": "2026-05-05T15:00:00+05:00",
      "title": "Chris Redd: Why Am I Like This?",
      "desc": "Chris Redd digs into his days of living life like a music video and realizing that even if he'll never be tall enough to dunk, he can still grow as a person.",
      "date": "2022",
      "language": "en",
      "categories": [
        "Special",
        "Standup"
      ],
      "icon": "http://dtil.tmsimg.com/assets/p23246103_b_h8_aa.jpg?w=960&h=540",
      "credits": {
        "director": [
          "Richie Keen"
        ],
        "actor": [
          "Chris Redd"
        ]
      }
    },
    {
      "start": "2026-05-05T15:00:00+05:00",
      "stop": "2026-05-05T15:25:00+05:00",
      "title": "Corner Gas",
      "sub_title": "Full Load",
      "desc": "Lacey is the unlikely champion of an eating contest; Emma enjoys the pleasures of an MP3 player.",
      "date": "2008",
      "language": "en",
      "rating": "TVPG",
      "categories": [
        "Series",
        "Sitcom"
      ],
      "episode": "S6 E1",
      "icon": "http://dtil.tmsimg.com/assets/p8495876_b_h10_aa.jpg?w=960&h=540",
      "credits": {
        "actor": [
          "Brent Butt",
          "Eric Peterson",
          "Janet Wright"
        ]
      }
    },
    {
      "start": "2026-05-05T15:25:00+05:00",
      "stop": "2026-05-05T15:50:00+05:00",
      "title": "Corner Gas",
      "sub_title": "Bend it Like Brent",
      "desc": "Brent and Lacey sponsor Davis' football team; Karen's reckless driving puts Hank in the driver's seat.",
      "date": "2008",
      "language": "en",
      "rating": "TVPG",
      "categories": [
        "Series",
        "Sitcom"
      ],
      "episode": "S6 E2",
      "icon": "http://dtil.tmsimg.com/assets/p8495876_b_h10_aa.jpg?w=960&h=540",
      "credits": {
        "actor": [
          "Brent Butt",
          "Eric Peterson",
          "Janet Wright"
        ]
      }
    }
  ]
}