{
  "channels": [
    {}
  ],
  "programs": [
    {
      "start": "2026-05-07T09:30:00+05:00",
      "stop": "2026-05-07T10:00:00+05:00",
      "title": "How Do They Do It? 11",
      "sub_title": "bajal",
      "desc": "Documentary filmmakers reveal the secrets of the production of objects and devices.They meet inventive engineers and designers whose life mission is to improve reality.",
      "language": "en",
      "categories": [
        "Documentary Series"
      ],
      "episode": "S11"
    },
    {
      "start": "2026-05-07T10:00:00+05:00",
      "stop": "2026-05-07T10:30:00+05:00",
      "title": "How Do They Do It? 11",
      "sub_title": "Garbage in Venice",
      "desc": "Documentary filmmakers reveal the secrets of the production of objects and devices.They meet inventive engineers and designers whose life mission is to improve reality.",
      "language": "en",
      "categories": [
        "Documentary Series"
      ],
      "episode": "S11"
    },
    {
      "start": "2026-05-07T10:30:00+05:00",
      "stop": "2026-05-07T11:00:00+05:00",
      "title": "How Do They Do It? 11",
      "sub_title": "Turkish delicacy",
      "desc": "Documentary filmmakers reveal the secrets of the production of objects and devices.They meet inventive engineers and designers whose life mission is to improve reality.",
      "language": "en",
      "categories": [
        "Documentary Series"
      ],
      "episode": "S11"
    },
    {
      "start": "2026-05-07T11:00:00+05:00",
      "stop": "2026-05-07T12:00:00+05:00",
      "title": "How the Universe Works 5",
      "sub_title": "The mysterious history of Pluto",
      "desc": "A series presenting the elements that make up the Universe.Thanks to computer graphics, viewers will be able to see unusual astronomical objects found in space.",
      "date": "2016",
      "language": "en",
      "categories": [
        "Documentary Series"
      ],
      "episode": "S5"
    },
    {
      "start": "2026-05-07T12:00:00+05:00",
      "stop": "2026-05-07T13:00:00+05:00",
      "title": "How the Universe Works 5",
      "sub_title": "The mystery of dark matter",
      "desc": "A series presenting the elements that make up the Universe.Thanks to computer graphics, viewers will be able to see unusual astronomical objects found in space.",
      "date": "2016",
      "language": "en",
      "categories": [
        "Documentary Series"
      ],
      "episode": "S5"
    },
    {
      "start": "2026-05-07T13:00:00+05:00",
      "stop": "2026-05-07T14:00:00+05:00",
      "title": "How the Universe Works 5",
      "sub_title": "The strangest planets",
      "desc": "A series presenting the elements that make up the Universe.Thanks to computer graphics, viewers will be able to see unusual astronomical objects found in space.",
      "date": "2016",
      "language": "en",
      "categories": [
        "Documentary Series"
      ],
      "episode": "S5"
    }
  ]
}