{
  "channels": [
    {}
  ],
  "programs": [
    {
      "start": "2026-05-06T04:00:00+05:00",
      "stop": "2026-05-06T04:30:00+05:00",
      "title": "Bob's Burgers",
      "sub_title": "The Fresh Princ-ipal",
      "desc": "Things get out of hand when Louise wins a contest to be principal for a day; Teddy has a unique suggestion to help Bob when he suddenly finds himself unable to flip burgers.",
      "date": "2019",
      "language": "en",
      "rating": "TVPG",
      "categories": [
        "Series",
        "Animated",
        "Sitcom"
      ],
      "episode": "S9 E15",
      "icon": "http://dtil.tmsimg.com/assets/p8127591_b_h8_ah.jpg?w=960&h=540",
      "credits": {
        "actor": [
          "H. Jon Benjamin",
          "Dan Mintz",
          "Eugene Mirman"
        ]
      }
    },
    {
      "start": "2026-05-06T04:30:00+05:00",
      "stop": "2026-05-06T05:00:00+05:00",
      "title": "Bob's Burgers",
      "sub_title": "Roamin' Bob-iday",
      "desc": "The family forces Bob to take a much-needed day off, only for him to wind up working at a local sandwich shop; Linda and the kids throw a last-minute baby shower at the restaurant for a female biker group.",
      "date": "2019",
      "language": "en",
      "rating": "TVPG",
      "categories": [
        "Series",
        "Animated",
        "Sitcom"
      ],
      "episode": "S9 E16",
      "icon": "http://dtil.tmsimg.com/assets/p8127591_b_h8_ah.jpg?w=960&h=540",
      "credits": {
        "actor": [
          "H. Jon Benjamin",
          "Dan Mintz",
          "Eugene Mirman"
        ]
      }
    },
    {
      "start": "2026-05-06T05:00:00+05:00",
      "stop": "2026-05-06T05:30:00+05:00",
      "title": "Bob's Burgers",
      "sub_title": "What About Blob?",
      "desc": "Gene convinces Tina and Louise to help him save a misunderstood plankton blob from being destroyed by a yacht club.",
      "date": "2019",
      "language": "en",
      "rating": "TV14",
      "categories": [
        "Series",
        "Animated",
        "Sitcom"
      ],
      "episode": "S9 E17",
      "icon": "http://dtil.tmsimg.com/assets/p8127591_b_h8_ah.jpg?w=960&h=540",
      "credits": {
        "actor": [
          "H. Jon Benjamin",
          "Dan Mintz",
          "Eugene Mirman"
        ]
      }
    },
    {
      "start": "2026-05-06T05:30:00+05:00",
      "stop": "2026-05-06T06:00:00+05:00",
      "title": "Bob's Burgers",
      "sub_title": "If You Love It So Much, Why Don't You Marionette?",
      "desc": "The kids visit a marionette theater for a school field trip, and Louise gets on the theater owner's bad side; Bob takes pity on a guy who's handing out flyers in front of the restaurant.",
      "date": "2019",
      "language": "en",
      "rating": "TVPG",
      "categories": [
        "Series",
        "Animated",
        "Sitcom"
      ],
      "episode": "S9 E18",
      "icon": "http://dtil.tmsimg.com/assets/p8127591_b_h8_ah.jpg?w=960&h=540",
      "credits": {
        "actor": [
          "H. Jon Benjamin",
          "Dan Mintz",
          "Eugene Mirman"
        ]
      }
    },
    {
      "start": "2026-05-06T06:00:00+05:00",
      "stop": "2026-05-06T06:30:00+05:00",
      "title": "Bob's Burgers",
      "sub_title": "Long Time Listener, First Time Bob",
      "desc": "When Bob meets his personal hero -- a renegade radio DJ who refuses to compromise -- the Belchers get in over their heads while trying to help him stage a comeback.",
      "date": "2019",
      "language": "en",
      "rating": "TV14",
      "categories": [
        "Series",
        "Animated",
        "Sitcom"
      ],
      "episode": "S9 E19",
      "icon": "http://dtil.tmsimg.com/assets/p8127591_b_h8_ah.jpg?w=960&h=540",
      "credits": {
        "actor": [
          "H. Jon Benjamin",
          "Dan Mintz",
          "Eugene Mirman"
        ]
      }
    },
    {
      "start": "2026-05-06T06:30:00+05:00",
      "stop": "2026-05-06T07:00:00+05:00",
      "title": "Bob's Burgers",
      "sub_title": "The Gene Mile",
      "desc": "When the kids have to run a mandatory mile for school on free-ice-cream day, they hatch an elaborate plot to sneak away; Bob and Linda frantically try to secure discount tickets to a show at the Wharf Arts Center.",
      "date": "2019",
      "language": "en",
      "rating": "TVPG",
      "categories": [
        "Series",
        "Animated",
        "Sitcom"
      ],
      "episode": "S9 E20",
      "icon": "http://dtil.tmsimg.com/assets/p8127591_b_h8_ah.jpg?w=960&h=540",
      "credits": {
        "actor": [
          "H. Jon Benjamin",
          "Dan Mintz",
          "Eugene Mirman"
        ]
      }
    }
  ]
}