{
  "channels": [
    {}
  ],
  "programs": [
    {
      "start": "2026-05-04T19:03:00+05:00",
      "stop": "2026-05-04T21:23:00+05:00",
      "title": "Sinners",
      "desc": "Trying to leave their troubled lives behind, twin brothers return to their Mississippi hometown to start again, only to discover that an even greater evil is waiting to welcome them back.",
      "date": "2025",
      "language": "en",
      "rating": "R",
      "categories": [
        "Movie",
        "Horror",
        "Thriller"
      ],
      "icon": "http://dtil.tmsimg.com/assets/p28380869_v_h8_ak.jpg?w=960&h=540",
      "credits": {
        "director": [
          "Ryan Coogler"
        ],
        "actor": [
          "Michael B. Jordan",
          "Hailee Steinfeld",
          "Miles Caton"
        ]
      }
    },
    {
      "start": "2026-05-04T21:23:00+05:00",
      "stop": "2026-05-04T22:04:00+05:00",
      "title": "Last Week Tonight With John Oliver",
      "desc": "Comedian John Oliver hosts an in-depth, satirical look at developments from the past seven days in news, politics and current events.",
      "date": "2026",
      "language": "en",
      "rating": "TVMA",
      "categories": [
        "Series",
        "Talk",
        "Comedy"
      ],
      "episode": "S13 E10",
      "icon": "http://dtil.tmsimg.com/assets/p32202276_b_h8_ac.jpg?w=960&h=540",
      "credits": {
        "actor": [
          "John Oliver"
        ]
      }
    },
    {
      "start": "2026-05-04T22:04:00+05:00",
      "stop": "2026-05-04T23:09:00+05:00",
      "title": "Half Man",
      "desc": "When Niall's estranged brother Ruben shows up at his wedding, it leads to an explosion of violence that catapults us back through their lives, from the eighties to the present day.",
      "date": "2026",
      "language": "en",
      "rating": "A18",
      "categories": [
        "Series",
        "Drama"
      ],
      "episode": "S1 E2",
      "icon": "http://dtil.tmsimg.com/assets/p32755220_b_h8_aa.jpg?w=960&h=540",
      "credits": {
        "director": [
          "Alexandra Brodski"
        ],
        "actor": [
          "Jamie Bell",
          "Richard Gadd",
          "Neve McIntosh"
        ]
      }
    },
    {
      "start": "2026-05-04T23:09:00+05:00",
      "stop": "2026-05-04T23:41:00+05:00",
      "title": "Rooster",
      "sub_title": "Ludlow's Fourth Hottest Professor",
      "desc": "Set on a college campus centering on an author's complicated relationship with his daughter.",
      "date": "2026",
      "language": "en",
      "rating": "TVMA",
      "categories": [
        "Series",
        "Comedy"
      ],
      "episode": "S1 E9",
      "icon": "http://dtil.tmsimg.com/assets/p32380281_b_h8_ae.jpg?w=960&h=540",
      "credits": {
        "actor": [
          "Steve Carell",
          "Charly Clive",
          "Danielle Deadwyler"
        ]
      }
    },
    {
      "start": "2026-05-04T23:41:00+05:00",
      "stop": "2026-05-05T00:15:00+05:00",
      "title": "The Comeback",
      "desc": "A television actress tries desperately to revive her career.",
      "date": "2026",
      "language": "en",
      "rating": "TVMA",
      "categories": [
        "Series",
        "Sitcom",
        "Comedy"
      ],
      "episode": "S3 E7",
      "icon": "http://dtil.tmsimg.com/assets/p32424721_b_h8_ag.jpg?w=960&h=540",
      "credits": {
        "actor": [
          "Lisa Kudrow",
          "Robert Michael Morris",
          "Damian Young"
        ]
      }
    },
    {
      "start": "2026-05-05T00:15:00+05:00",
      "stop": "2026-05-05T01:20:00+05:00",
      "title": "Euphoria",
      "sub_title": "Kitty Likes To Dance",
      "desc": "A group of high school students navigates drugs, sex, identity, trauma, social media, love and friendship.",
      "date": "2026",
      "language": "en",
      "rating": "TVMA",
      "categories": [
        "Series",
        "Drama"
      ],
      "episode": "S3 E4",
      "icon": "http://dtil.tmsimg.com/assets/p32242506_b_h8_ac.jpg?w=960&h=540",
      "credits": {
        "actor": [
          "Zendaya",
          "Maude Apatow",
          "Angus Cloud"
        ]
      }
    }
  ]
}