{
  "channels": [
    {}
  ],
  "programs": [
    {
      "start": "2026-05-05T22:30:00+05:00",
      "stop": "2026-05-05T23:00:00+05:00",
      "title": "House Hunters International",
      "sub_title": "NYC Woman Seeks Love in Amsterdam",
      "desc": "An NYC woman leaves everything for one last shot at finding love and starting a family in Amsterdam; she searches for her dream man as well as the dream apartment, but with Amsterdam's housing crunch, those dreams may be in jeopardy.",
      "date": "2024",
      "language": "en",
      "rating": "TVG",
      "categories": [
        "Series",
        "Reality",
        "Travel",
        "House/garden"
      ],
      "episode": "S194 E9",
      "icon": "http://dtil.tmsimg.com/assets/p185817_b_h8_co.jpg?w=960&h=540",
      "credits": {
        "actor": [
          "Andromeda Dunker"
        ]
      }
    },
    {
      "start": "2026-05-05T23:00:00+05:00",
      "stop": "2026-05-05T23:30:00+05:00",
      "title": "House Hunters International",
      "sub_title": "Community Connection vs. Comfort in Tulum, Mexico",
      "desc": "A couple looks to escape their hectic Miami lives and slow down in Tulum, Mexico; he pictures a walker's paradise in the heart of the older downtown, but she wants a spacious and luxurious new build in the suburbs.",
      "date": "2024",
      "language": "en",
      "rating": "TVG",
      "categories": [
        "Series",
        "Reality",
        "Travel",
        "House/garden"
      ],
      "episode": "S194 E10",
      "icon": "http://dtil.tmsimg.com/assets/p185817_b_h8_co.jpg?w=960&h=540",
      "credits": {
        "actor": [
          "Andromeda Dunker"
        ]
      }
    },
    {
      "start": "2026-05-05T23:30:00+05:00",
      "stop": "2026-05-06T00:00:00+05:00",
      "title": "House Hunters International",
      "sub_title": "The Return of Ciao House, Puglia Edition",
      "desc": "The celebrity chef of \"Ciao House\" is back again this season; the stakes are even higher as he hunts for a seaside farmhouse in Southern Italy.",
      "date": "2024",
      "language": "en",
      "rating": "TVG",
      "categories": [
        "Series",
        "Reality",
        "Travel",
        "House/garden"
      ],
      "episode": "S194 E11",
      "icon": "http://dtil.tmsimg.com/assets/p185817_b_h8_co.jpg?w=960&h=540",
      "credits": {
        "actor": [
          "Andromeda Dunker"
        ]
      }
    },
    {
      "start": "2026-05-06T00:00:00+05:00",
      "stop": "2026-05-06T00:30:00+05:00",
      "title": "House Hunters International",
      "sub_title": "Family Time in Valencia, Spain",
      "desc": "After their daughter's birth, a young couple leaves Florida for a better work-life balance in Valencia, Spain; he's hoping to replicate the space and luxury of their suburban home, but she's looking to enjoy city life and save money for traveling.",
      "date": "2024",
      "language": "en",
      "rating": "TVG",
      "categories": [
        "Series",
        "Reality",
        "Travel",
        "House/garden"
      ],
      "episode": "S194 E12",
      "icon": "http://dtil.tmsimg.com/assets/p185817_b_h8_co.jpg?w=960&h=540",
      "credits": {
        "actor": [
          "Andromeda Dunker"
        ]
      }
    },
    {
      "start": "2026-05-06T00:30:00+05:00",
      "stop": "2026-05-06T01:00:00+05:00",
      "title": "House Hunters International",
      "sub_title": "Adventurous Oregon Family Goes Dutch",
      "desc": "Charmed by an Amsterdam vacation, an adventurous Oregon family looks to relocate and go all-in on the Dutch way of life; dad looks to experience life in the city, but mom wants the kind of spaciousness that's only found in the outskirts.",
      "date": "2024",
      "language": "en",
      "rating": "TVG",
      "categories": [
        "Series",
        "Reality",
        "Travel",
        "House/garden"
      ],
      "episode": "S194 E13",
      "icon": "http://dtil.tmsimg.com/assets/p185817_b_h8_co.jpg?w=960&h=540",
      "credits": {
        "actor": [
          "Andromeda Dunker"
        ]
      }
    },
    {
      "start": "2026-05-06T01:00:00+05:00",
      "stop": "2026-05-06T01:30:00+05:00",
      "title": "House Hunters International",
      "sub_title": "Recapturing the Excitement of Their Youth in La Drova, Spain",
      "desc": "After 30 years together, two ex-circus performers decide to shake up their quiet life and relocate to La Drova, Spain; he wants a secluded standalone house and doesn't mind reno projects, but she wants a traditional Spanish home that's move-in ready.",
      "date": "2024",
      "language": "en",
      "rating": "TVG",
      "categories": [
        "Series",
        "Reality",
        "Travel",
        "House/garden"
      ],
      "episode": "S195 E1",
      "icon": "http://dtil.tmsimg.com/assets/p185817_b_h8_co.jpg?w=960&h=540",
      "credits": {
        "actor": [
          "Andromeda Dunker"
        ]
      }
    }
  ]
}