{
  "channels": [
    {}
  ],
  "programs": [
    {
      "start": "2026-05-05T21:00:00+05:00",
      "stop": "2026-05-05T21:30:00+05:00",
      "title": "Night Court",
      "sub_title": "My Three Dads",
      "desc": "Harry, Bull and Dan (Harry Anderson, Richard Moll, John Larroquette) all pitch in to help at Christine's (Markie Post) Lamaze class.",
      "date": "1990",
      "language": "en",
      "rating": "TVPG",
      "categories": [
        "Series",
        "Sitcom"
      ],
      "episode": "S7 E21",
      "icon": "http://dtil.tmsimg.com/assets/p184004_b_h10_ab.jpg?w=960&h=540",
      "credits": {
        "actor": [
          "Harry Anderson",
          "John Larroquette",
          "Richard Moll"
        ]
      }
    },
    {
      "start": "2026-05-05T21:30:00+05:00",
      "stop": "2026-05-05T22:00:00+05:00",
      "title": "Night Court",
      "sub_title": "Still Another Day in the Life",
      "desc": "The court tries to conduct business while loud construction work takes place upstairs. With Harry Anderson and Markie Post.",
      "date": "1990",
      "language": "en",
      "rating": "TVPG",
      "categories": [
        "Series",
        "Sitcom"
      ],
      "episode": "S7 E22",
      "icon": "http://dtil.tmsimg.com/assets/p184004_b_h10_ab.jpg?w=960&h=540",
      "credits": {
        "actor": [
          "Harry Anderson",
          "John Larroquette",
          "Richard Moll"
        ]
      }
    },
    {
      "start": "2026-05-05T22:00:00+05:00",
      "stop": "2026-05-05T22:30:00+05:00",
      "title": "Night Court",
      "sub_title": "A Closer Look",
      "desc": "Television viewers get an eyeful when the cameras of \"A Closer Look\" invade Harry's (Harry Anderson) courtroom. Bob Sarlatte guest stars. With Markie Post.",
      "date": "1990",
      "language": "en",
      "rating": "TVPG",
      "categories": [
        "Series",
        "Sitcom"
      ],
      "episode": "S7 E23",
      "icon": "http://dtil.tmsimg.com/assets/p184004_b_h10_ab.jpg?w=960&h=540",
      "credits": {
        "actor": [
          "Harry Anderson",
          "John Larroquette",
          "Richard Moll"
        ]
      }
    },
    {
      "start": "2026-05-05T22:30:00+05:00",
      "stop": "2026-05-05T23:00:00+05:00",
      "title": "Night Court",
      "sub_title": "The Blues of the Birth",
      "desc": "Christine (Markie Post) goes into labor while she's stuck in a courthouse elevator with Buddy and a stranger (John Astin, Stephen Furst).",
      "date": "1990",
      "language": "en",
      "rating": "TVPG",
      "categories": [
        "Series",
        "Sitcom"
      ],
      "episode": "S7 E24",
      "icon": "http://dtil.tmsimg.com/assets/p184004_b_h10_ab.jpg?w=960&h=540",
      "credits": {
        "actor": [
          "Harry Anderson",
          "John Larroquette",
          "Richard Moll"
        ]
      }
    },
    {
      "start": "2026-05-05T23:00:00+05:00",
      "stop": "2026-05-05T23:30:00+05:00",
      "title": "Night Court",
      "sub_title": "A Family Affair",
      "desc": "Dan's sister (Susan Diol), who is cut from the same cloth, drops by for a visit and a \"fling.\" With Harry Anderson and John Larroquette.",
      "date": "1990",
      "language": "en",
      "rating": "TVPG",
      "categories": [
        "Series",
        "Sitcom"
      ],
      "episode": "S8 E1 P1/2",
      "icon": "http://dtil.tmsimg.com/assets/p184004_b_h10_ab.jpg?w=960&h=540",
      "credits": {
        "actor": [
          "Harry Anderson",
          "John Larroquette",
          "Richard Moll"
        ]
      }
    },
    {
      "start": "2026-05-05T23:30:00+05:00",
      "stop": "2026-05-06T00:00:00+05:00",
      "title": "Night Court",
      "sub_title": "A Family Affair",
      "desc": "Bull (Richard Moll) proposes to Dan's amorous sister (Susan Diol) after being accused of seducing her. With John Larroquette.",
      "date": "1990",
      "language": "en",
      "rating": "TVPG",
      "categories": [
        "Series",
        "Sitcom"
      ],
      "episode": "S8 E2 P2/2",
      "icon": "http://dtil.tmsimg.com/assets/p184004_b_h10_ab.jpg?w=960&h=540",
      "credits": {
        "actor": [
          "Harry Anderson",
          "John Larroquette",
          "Richard Moll"
        ]
      }
    }
  ]
}