{
  "channels": [
    {}
  ],
  "programs": [
    {
      "start": "2026-05-05T01:00:00+05:00",
      "stop": "2026-05-05T02:00:00+05:00",
      "title": "Dr. Pimple Popper: Breaking Out",
      "sub_title": "Superglue to the Rescue",
      "desc": "Tierra is a musician with massive bumps on her ears that hold her back from performing.",
      "date": "2025",
      "language": "en",
      "rating": "13+",
      "categories": [
        "Series",
        "Health",
        "Entertainment"
      ],
      "episode": "S1 E3",
      "icon": "http://dtil.tmsimg.com/assets/p29725512_b_h8_ag.jpg?w=960&h=540",
      "credits": {
        "actor": [
          "Sandra Lee"
        ]
      }
    },
    {
      "start": "2026-05-05T02:00:00+05:00",
      "stop": "2026-05-05T03:00:00+05:00",
      "title": "Dr. Pimple Popper: Breaking Out",
      "sub_title": "Lessons in Pimple Popping",
      "desc": "\"Dottie the Body\" lost her confidence when a large bump started growing between her thighs; Dr. Lee brings in a new, young doctor to help Tim with his big, bumpy nose; Karime is insecure about her birthmark that looks like a black eye.",
      "date": "2025",
      "language": "en",
      "rating": "13+",
      "categories": [
        "Series",
        "Health",
        "Entertainment"
      ],
      "episode": "S1 E1",
      "icon": "http://dtil.tmsimg.com/assets/p29725512_b_h8_ag.jpg?w=960&h=540",
      "credits": {
        "actor": [
          "Sandra Lee"
        ]
      }
    },
    {
      "start": "2026-05-05T03:00:00+05:00",
      "stop": "2026-05-05T04:00:00+05:00",
      "title": "Dr. Pimple Popper: Breaking Out",
      "sub_title": "Third Eye Blinded",
      "desc": "Allie's lifestyle is ruined by the gumball-sized bump above her eye; Andrew's psoriasis and multiple body bumps have held him back from starting a family; Dr. Lyndsey assists Dr. Lee with Cristina's concerning shoulder lipoma.",
      "date": "2025",
      "language": "en",
      "rating": "13+",
      "categories": [
        "Series",
        "Health",
        "Entertainment"
      ],
      "episode": "S1 E17",
      "icon": "http://dtil.tmsimg.com/assets/p29725512_b_h8_ag.jpg?w=960&h=540",
      "credits": {
        "director": [
          "Kim Chessler"
        ],
        "actor": [
          "Sandra Lee"
        ]
      }
    },
    {
      "start": "2026-05-05T04:00:00+05:00",
      "stop": "2026-05-05T05:00:00+05:00",
      "title": "Dr. Pimple Popper: Breaking Out",
      "sub_title": "A Mother's Lump",
      "desc": "Angela has a big, melon-sized growth on the back of her neck that she fears can ruin her daughter's wedding; Loretta is terrified that her painful can get in the way of making her movie.",
      "date": "2026",
      "language": "en",
      "rating": "TVPG",
      "categories": [
        "Series",
        "Health",
        "Entertainment"
      ],
      "episode": "S2 E1",
      "icon": "http://dtil.tmsimg.com/assets/p29725512_b_h8_ag.jpg?w=960&h=540",
      "credits": {
        "actor": [
          "Sandra Lee"
        ]
      }
    },
    {
      "start": "2026-05-05T05:00:00+05:00",
      "stop": "2026-05-05T06:00:00+05:00",
      "title": "Dr. Pimple Popper: Breaking Out",
      "sub_title": "Gone in CYST-Y Seconds",
      "desc": "John is a sweet guy trying to get over his bumpy past; Tami has yellow deposits on her eyelids that make it impossible for her to feel beautiful; Dr. Farhang helps Dr. Lee with a terrified patient, Lili, who has a lump on the back of her arm.",
      "date": "2026",
      "language": "en",
      "rating": "TVPG",
      "categories": [
        "Series",
        "Health",
        "Entertainment"
      ],
      "episode": "S2 E2",
      "icon": "http://dtil.tmsimg.com/assets/p29725512_b_h8_ag.jpg?w=960&h=540",
      "credits": {
        "actor": [
          "Sandra Lee"
        ]
      }
    },
    {
      "start": "2026-05-05T06:00:00+05:00",
      "stop": "2026-05-05T07:03:00+05:00",
      "title": "Dr. Pimple Popper: Breaking Out",
      "sub_title": "A Cheeky Bump",
      "desc": "Dave has 17 huge, painful head bumps; Melissa recently moved to a new town but her mysterious red, scaly lesions cover her legs; Glamorous dermatologist Dr. Shearer Seymour shadows Dr. Lee as they attempt to remove a pointy cyst from Sam's cheek.",
      "date": "2026",
      "language": "en",
      "rating": "TVPG",
      "categories": [
        "Series",
        "Health",
        "Entertainment"
      ],
      "episode": "S2 E3",
      "icon": "http://dtil.tmsimg.com/assets/p32658290_b_h8_ac.jpg?w=960&h=540",
      "credits": {
        "actor": [
          "Sandra Lee"
        ]
      }
    }
  ]
}