{
  "channels": [
    {}
  ],
  "programs": [
    {
      "start": "2026-05-05T20:00:00+05:00",
      "stop": "2026-05-05T21:00:00+05:00",
      "title": "Bar Rescue",
      "sub_title": "The Perks of Being a Wallpaper",
      "desc": "A classic dive bar with mob ties in Las Vegas is about to close its doors because of an owner who's busy being a nice guy rather than a wise guy.",
      "date": "2016",
      "language": "en",
      "rating": "TVPG",
      "categories": [
        "Series",
        "Reality"
      ],
      "episode": "S5 E1",
      "icon": "http://dtil.tmsimg.com/assets/p8692405_b_h8_ah.jpg?w=960&h=540",
      "credits": {
        "actor": [
          "Jon Taffer"
        ]
      }
    },
    {
      "start": "2026-05-05T21:00:00+05:00",
      "stop": "2026-05-05T22:00:00+05:00",
      "title": "Bar Rescue",
      "sub_title": "Liv'n on a Prayer",
      "desc": "Liv can't figure out exactly what her business is in order to survive in the highly competitive service town of Las Vegas.",
      "date": "2019",
      "language": "en",
      "rating": "TVPG",
      "categories": [
        "Series",
        "Reality"
      ],
      "episode": "S6 E34",
      "icon": "http://dtil.tmsimg.com/assets/p8692405_b_h8_ah.jpg?w=960&h=540",
      "credits": {
        "actor": [
          "Jon Taffer"
        ]
      }
    },
    {
      "start": "2026-05-05T22:00:00+05:00",
      "stop": "2026-05-05T23:00:00+05:00",
      "title": "Bar Rescue",
      "sub_title": "Raging Turkey",
      "desc": "Jon Taffer helps a defiant owner take responsibility for his failures in order to save himself from ruin.",
      "date": "2020",
      "language": "en",
      "rating": "TVPG",
      "categories": [
        "Series",
        "Reality"
      ],
      "episode": "S7 E10",
      "icon": "http://dtil.tmsimg.com/assets/p8692405_b_h8_ah.jpg?w=960&h=540",
      "credits": {
        "actor": [
          "Jon Taffer"
        ]
      }
    },
    {
      "start": "2026-05-05T23:00:00+05:00",
      "stop": "2026-05-06T00:00:00+05:00",
      "title": "Bar Rescue",
      "sub_title": "Two Tickets to Paradise Cantina",
      "desc": "In his hometown of Las Vegas, Jon rescues a beloved party bar that blames its downfall on the pandemic, until Jon discovers the truth.",
      "date": "2021",
      "language": "en",
      "rating": "TV14",
      "categories": [
        "Series",
        "Reality"
      ],
      "episode": "S8 E1",
      "icon": "http://dtil.tmsimg.com/assets/p8692405_b_h8_ah.jpg?w=960&h=540",
      "credits": {
        "actor": [
          "Jon Taffer"
        ]
      }
    },
    {
      "start": "2026-05-06T00:00:00+05:00",
      "stop": "2026-05-06T01:00:00+05:00",
      "title": "Bar Rescue",
      "sub_title": "Bad Times at Goodtime",
      "desc": "Jon Taffer sends mixologist Phil Wills to Inkster, Minn., to help three lifelong friends save their neighborhood bar and their friendship.",
      "date": "2025",
      "language": "en",
      "rating": "TV14",
      "categories": [
        "Series",
        "Reality"
      ],
      "episode": "S9 E35",
      "icon": "http://dtil.tmsimg.com/assets/p8692405_b_h8_ah.jpg?w=960&h=540",
      "credits": {
        "actor": [
          "Jon Taffer",
          "Phil Wills"
        ]
      }
    },
    {
      "start": "2026-05-06T01:00:00+05:00",
      "stop": "2026-05-06T02:00:00+05:00",
      "title": "Bar Rescue",
      "sub_title": "Game Over",
      "desc": "Jon heads to Sanford, Florida to revitalize a retro-arcade bar that is falling apart and an owner who has an excuse for everything.",
      "date": "2022",
      "language": "en",
      "rating": "TV14",
      "categories": [
        "Series",
        "Reality"
      ],
      "episode": "S8 E23",
      "icon": "http://dtil.tmsimg.com/assets/p8692405_b_h8_ah.jpg?w=960&h=540",
      "credits": {
        "actor": [
          "Jon Taffer"
        ]
      }
    }
  ]
}