{
  "channels": [
    {}
  ],
  "programs": [
    {
      "start": "2026-05-06T04:00:00+05:00",
      "stop": "2026-05-06T04:30:00+05:00",
      "title": "Mom",
      "sub_title": "Blow and a Free McMuffin",
      "desc": "Christy and Bonnie rush to sick Violet's side, only to find out that having mono is the least of her problems.",
      "date": "2016",
      "language": "en",
      "rating": "TV14",
      "categories": [
        "Series",
        "Sitcom"
      ],
      "episode": "S4 E5",
      "icon": "http://dtil.tmsimg.com/assets/p9978206_b_h8_as.jpg?w=960&h=540",
      "credits": {
        "director": [
          "James Widdoes"
        ],
        "actor": [
          "Anna Faris",
          "Allison Janney",
          "Sadie Calvano"
        ]
      }
    },
    {
      "start": "2026-05-06T04:30:00+05:00",
      "stop": "2026-05-06T05:00:00+05:00",
      "title": "Mom",
      "sub_title": "Xanax and a Baby Duck",
      "desc": "Christy becomes overprotective of her 12-year-old son when she discovers he's been using drugs and alcohol.",
      "date": "2016",
      "language": "en",
      "rating": "TV14",
      "categories": [
        "Series",
        "Sitcom"
      ],
      "episode": "S4 E6",
      "icon": "http://dtil.tmsimg.com/assets/p9978206_b_h8_as.jpg?w=960&h=540",
      "credits": {
        "director": [
          "Jon Cryer"
        ],
        "actor": [
          "Anna Faris",
          "Allison Janney",
          "Mimi Kennedy"
        ]
      }
    },
    {
      "start": "2026-05-06T05:00:00+05:00",
      "stop": "2026-05-06T05:30:00+05:00",
      "title": "Mom",
      "sub_title": "A Judgy Face and Your Grandma's Drawers",
      "desc": "Christy, Bonnie and the ladies step in to help when Marjorie babysits her granddaughter for the first time.",
      "date": "2020",
      "language": "en",
      "rating": "TV14",
      "categories": [
        "Series",
        "Sitcom"
      ],
      "episode": "S7 E18",
      "icon": "http://dtil.tmsimg.com/assets/p9978206_b_h8_as.jpg?w=960&h=540",
      "credits": {
        "director": [
          "James Widdoes"
        ],
        "actor": [
          "Anna Faris",
          "Allison Janney",
          "Mimi Kennedy"
        ]
      }
    },
    {
      "start": "2026-05-06T05:30:00+05:00",
      "stop": "2026-05-06T06:00:00+05:00",
      "title": "Mom",
      "sub_title": "Big Sad Eyes and an Antique Hot Dog",
      "desc": "The ladies' friendships are tested when they live in close quarters during a sober retreat.",
      "date": "2020",
      "language": "en",
      "rating": "TV14",
      "categories": [
        "Series",
        "Sitcom"
      ],
      "episode": "S7 E20",
      "icon": "http://dtil.tmsimg.com/assets/p9978206_b_h8_as.jpg?w=960&h=540",
      "credits": {
        "director": [
          "James Widdoes"
        ],
        "actor": [
          "Anna Faris",
          "Allison Janney",
          "Mimi Kennedy"
        ]
      }
    },
    {
      "start": "2026-05-06T06:00:00+05:00",
      "stop": "2026-05-06T08:30:00+05:00",
      "title": "Bad Moms",
      "desc": "Amy (Mila Kunis) has a great husband, overachieving children, beautiful home and successful career. Unfortunately, she's also overworked, exhausted and ready to snap. Fed up, she joins forces with two other stressed-out mothers (Kristen Bell, Kathryn Hahn) to get away from daily life and conventional responsibilities. As the gals go wild with their newfound freedom, they set themselves up for the ultimate showdown with PTA queen bee Gwendolyn and her clique of seemingly perfect moms.",
      "date": "2016",
      "language": "en",
      "rating": "R",
      "categories": [
        "Movie",
        "Comedy"
      ],
      "icon": "http://dtil.tmsimg.com/assets/p12706834_v_h8_ac.jpg?w=960&h=540",
      "credits": {
        "director": [
          "Jon Lucas",
          "Scott Moore"
        ],
        "actor": [
          "Mila Kunis",
          "Kristen Bell",
          "Kathryn Hahn"
        ]
      }
    },
    {
      "start": "2026-05-06T08:30:00+05:00",
      "stop": "2026-05-06T10:30:00+05:00",
      "title": "The Stepford Wives",
      "desc": "After enduring setbacks in her television career, executive Joanna Eberhart (Nicole Kidman) relocates with her family from New York City to the Connecticut suburb of Stepford. While Joanna's husband, Walter (Matthew Broderick), quickly warms up to their new town, she has a hard time adjusting to Stepford's manicured environs and the overly accommodating attitude of the area women. Soon Joanna begins to suspect that something is not right, and she tries to uncover Stepford's secret.",
      "date": "2004",
      "language": "en",
      "rating": "PG-13",
      "categories": [
        "Movie",
        "Dark comedy",
        "Horror",
        "Thriller",
        "Science fiction"
      ],
      "icon": "http://dtil.tmsimg.com/assets/p34618_v_h8_ai.jpg?w=960&h=540",
      "credits": {
        "director": [
          "Frank Oz"
        ],
        "actor": [
          "Nicole Kidman",
          "Matthew Broderick",
          "Bette Midler"
        ]
      }
    }
  ]
}