<?xml version='1.0' encoding='utf-8'?>
<tv>
  <channel id="9-Mystery-and-Paranormal-AU">
    <display-name>9 Mystery &amp; Paranormal</display-name>
    <icon src="https://thefilmtuition.com/tvlogo/9-Mystery-and-Paranormal-AU.png" />
  </channel><programme channel="9-Mystery-and-Paranormal-AU" start="20260503093935 +0500" stop="20260503102606 +0500">
    <title>Alien Encounters: Fact Or Fiction</title>
    <sub-title>Proof From Area 51</sub-title>
    <desc>9Mystery &amp; Paranormal provides supernatural documentaries, unexplained phenomena, and mystery-focused entertainment programming.</desc>
    <episode-num system="onscreen">S01E05</episode-num>
    <language>en</language>
    <rating system="ACB">
      <value>M</value>
    </rating>
  </programme><programme channel="9-Mystery-and-Paranormal-AU" start="20260503102606 +0500" stop="20260503112606 +0500">
    <title>Mystery &amp; Paranormal Show</title>
    <desc>9Mystery &amp; Paranormal provides supernatural documentaries, unexplained phenomena, and mystery-focused entertainment programming.</desc>
    <language>en</language>
  </programme><programme channel="9-Mystery-and-Paranormal-AU" start="20260503112606 +0500" stop="20260503120023 +0500">
    <title>Mystery &amp; Paranormal Show</title>
    <desc>9Mystery &amp; Paranormal provides supernatural documentaries, unexplained phenomena, and mystery-focused entertainment programming.</desc>
    <category>Mystery</category>
    <language>en</language>
  </programme><programme channel="9-Mystery-and-Paranormal-AU" start="20260503120023 +0500" stop="20260503124726 +0500">
    <title>Ghost Adventures</title>
    <sub-title>The Chinatown Poltergeist</sub-title>
    <desc>(M) The crew investigate poltergeist activity at a tiki bar in Las Vegas. A shooting there in 1995 may be responsible for moving objects and ghost sightings.</desc>
    <episode-num system="onscreen">S17E08</episode-num>
    <category>Paranormal</category>
    <language>en</language>
    <rating system="ACB">
      <value>M</value>
    </rating>
  </programme><programme channel="9-Mystery-and-Paranormal-AU" start="20260503124726 +0500" stop="20260503133428 +0500">
    <title>Ghost Adventures</title>
    <sub-title>Beneath the Bonanza</sub-title>
    <desc>9Mystery &amp; Paranormal provides supernatural documentaries, unexplained phenomena, and mystery-focused entertainment programming.</desc>
    <episode-num system="onscreen">S17E09</episode-num>
    <category>Paranormal</category>
    <language>en</language>
    <rating system="ACB">
      <value>M</value>
    </rating>
  </programme><programme channel="9-Mystery-and-Paranormal-AU" start="20260503133428 +0500" stop="20260503143428 +0500">
    <title>Mystery &amp; Paranormal Show</title>
    <desc>9Mystery &amp; Paranormal provides supernatural documentaries, unexplained phenomena, and mystery-focused entertainment programming.</desc>
    <category>Mystery</category>
    <language>en</language>
  </programme><programme channel="9-Mystery-and-Paranormal-AU" start="20260503143428 +0500" stop="20260503153428 +0500">
    <title>Mystery &amp; Paranormal Show</title>
    <desc>9Mystery &amp; Paranormal provides supernatural documentaries, unexplained phenomena, and mystery-focused entertainment programming.</desc>
    <category>Mystery</category>
    <language>en</language>
  </programme><programme channel="9-Mystery-and-Paranormal-AU" start="20260503153428 +0500" stop="20260503163428 +0500">
    <title>Mystery &amp; Paranormal Show</title>
    <desc>9Mystery &amp; Paranormal provides supernatural documentaries, unexplained phenomena, and mystery-focused entertainment programming.</desc>
    <category>Mystery</category>
    <language>en</language>
  </programme><programme channel="9-Mystery-and-Paranormal-AU" start="20260503163428 +0500" stop="20260503173428 +0500">
    <title>Mystery &amp; Paranormal Show</title>
    <desc>9Mystery &amp; Paranormal provides supernatural documentaries, unexplained phenomena, and mystery-focused entertainment programming.</desc>
    <category>Mystery</category>
    <language>en</language>
  </programme><programme channel="9-Mystery-and-Paranormal-AU" start="20260503173428 +0500" stop="20260503183428 +0500">
    <title>Mystery &amp; Paranormal Show</title>
    <desc>9Mystery &amp; Paranormal provides supernatural documentaries, unexplained phenomena, and mystery-focused entertainment programming.</desc>
    <category>Mystery</category>
    <language>en</language>
  </programme><programme channel="9-Mystery-and-Paranormal-AU" start="20260503183428 +0500" stop="20260503193428 +0500">
    <title>Mystery &amp; Paranormal Show</title>
    <desc>9Mystery &amp; Paranormal provides supernatural documentaries, unexplained phenomena, and mystery-focused entertainment programming.</desc>
    <category>Mystery</category>
    <language>en</language>
  </programme><programme channel="9-Mystery-and-Paranormal-AU" start="20260503193428 +0500" stop="20260503203428 +0500">
    <title>Mystery &amp; Paranormal Show</title>
    <desc>9Mystery &amp; Paranormal provides supernatural documentaries, unexplained phenomena, and mystery-focused entertainment programming.</desc>
    <category>Mystery</category>
    <language>en</language>
  </programme><programme channel="9-Mystery-and-Paranormal-AU" start="20260503203428 +0500" stop="20260503213428 +0500">
    <title>Mystery &amp; Paranormal Show</title>
    <desc>9Mystery &amp; Paranormal provides supernatural documentaries, unexplained phenomena, and mystery-focused entertainment programming.</desc>
    <category>Mystery</category>
    <language>en</language>
  </programme><programme channel="9-Mystery-and-Paranormal-AU" start="20260503213428 +0500" stop="20260503223428 +0500">
    <title>Mystery &amp; Paranormal Show</title>
    <desc>9Mystery &amp; Paranormal provides supernatural documentaries, unexplained phenomena, and mystery-focused entertainment programming.</desc>
    <category>Mystery</category>
    <language>en</language>
  </programme><programme channel="9-Mystery-and-Paranormal-AU" start="20260503223428 +0500" stop="20260503233428 +0500">
    <title>Mystery &amp; Paranormal Show</title>
    <desc>9Mystery &amp; Paranormal provides supernatural documentaries, unexplained phenomena, and mystery-focused entertainment programming.</desc>
    <category>Mystery</category>
    <language>en</language>
  </programme><programme channel="9-Mystery-and-Paranormal-AU" start="20260503233428 +0500" stop="20260504003428 +0500">
    <title>Mystery &amp; Paranormal Show</title>
    <desc>9Mystery &amp; Paranormal provides supernatural documentaries, unexplained phenomena, and mystery-focused entertainment programming.</desc>
    <category>Mystery</category>
    <language>en</language>
  </programme><programme channel="9-Mystery-and-Paranormal-AU" start="20260504003428 +0500" stop="20260504013428 +0500">
    <title>Mystery &amp; Paranormal Show</title>
    <desc>9Mystery &amp; Paranormal provides supernatural documentaries, unexplained phenomena, and mystery-focused entertainment programming.</desc>
    <category>Mystery</category>
    <language>en</language>
  </programme><programme channel="9-Mystery-and-Paranormal-AU" start="20260504013428 +0500" stop="20260504023428 +0500">
    <title>Mystery &amp; Paranormal Show</title>
    <desc>9Mystery &amp; Paranormal provides supernatural documentaries, unexplained phenomena, and mystery-focused entertainment programming.</desc>
    <category>Mystery</category>
    <language>en</language>
  </programme><programme channel="9-Mystery-and-Paranormal-AU" start="20260504023428 +0500" stop="20260504033428 +0500">
    <title>Mystery &amp; Paranormal Show</title>
    <desc>9Mystery &amp; Paranormal provides supernatural documentaries, unexplained phenomena, and mystery-focused entertainment programming.</desc>
    <category>Mystery</category>
    <language>en</language>
  </programme><programme channel="9-Mystery-and-Paranormal-AU" start="20260504033428 +0500" stop="20260504043428 +0500">
    <title>Mystery &amp; Paranormal Show</title>
    <desc>9Mystery &amp; Paranormal provides supernatural documentaries, unexplained phenomena, and mystery-focused entertainment programming.</desc>
    <category>Mystery</category>
    <language>en</language>
  </programme><programme channel="9-Mystery-and-Paranormal-AU" start="20260504043428 +0500" stop="20260504053428 +0500">
    <title>Mystery &amp; Paranormal Show</title>
    <desc>9Mystery &amp; Paranormal provides supernatural documentaries, unexplained phenomena, and mystery-focused entertainment programming.</desc>
    <category>Mystery</category>
    <language>en</language>
  </programme><programme channel="9-Mystery-and-Paranormal-AU" start="20260504053428 +0500" stop="20260504063428 +0500">
    <title>Mystery &amp; Paranormal Show</title>
    <desc>9Mystery &amp; Paranormal provides supernatural documentaries, unexplained phenomena, and mystery-focused entertainment programming.</desc>
    <category>Mystery</category>
    <language>en</language>
  </programme><programme channel="9-Mystery-and-Paranormal-AU" start="20260504063428 +0500" stop="20260504073428 +0500">
    <title>Mystery &amp; Paranormal Show</title>
    <desc>9Mystery &amp; Paranormal provides supernatural documentaries, unexplained phenomena, and mystery-focused entertainment programming.</desc>
    <category>Mystery</category>
    <language>en</language>
  </programme><programme channel="9-Mystery-and-Paranormal-AU" start="20260504073428 +0500" stop="20260504083428 +0500">
    <title>Mystery &amp; Paranormal Show</title>
    <desc>9Mystery &amp; Paranormal provides supernatural documentaries, unexplained phenomena, and mystery-focused entertainment programming.</desc>
    <category>Mystery</category>
    <language>en</language>
  </programme><programme channel="9-Mystery-and-Paranormal-AU" start="20260504083428 +0500" stop="20260504093428 +0500">
    <title>Mystery &amp; Paranormal Show</title>
    <desc>9Mystery &amp; Paranormal provides supernatural documentaries, unexplained phenomena, and mystery-focused entertainment programming.</desc>
    <category>Mystery</category>
    <language>en</language>
  </programme><programme channel="9-Mystery-and-Paranormal-AU" start="20260504093428 +0500" stop="20260504103428 +0500">
    <title>Mystery &amp; Paranormal Show</title>
    <desc>9Mystery &amp; Paranormal provides supernatural documentaries, unexplained phenomena, and mystery-focused entertainment programming.</desc>
    <category>Mystery</category>
    <language>en</language>
  </programme><programme channel="9-Mystery-and-Paranormal-AU" start="20260504103428 +0500" stop="20260504113428 +0500">
    <title>Mystery &amp; Paranormal Show</title>
    <desc>9Mystery &amp; Paranormal provides supernatural documentaries, unexplained phenomena, and mystery-focused entertainment programming.</desc>
    <category>Mystery</category>
    <language>en</language>
  </programme><programme channel="9-Mystery-and-Paranormal-AU" start="20260504113428 +0500" stop="20260504123428 +0500">
    <title>Mystery &amp; Paranormal Show</title>
    <desc>9Mystery &amp; Paranormal provides supernatural documentaries, unexplained phenomena, and mystery-focused entertainment programming.</desc>
    <category>Mystery</category>
    <language>en</language>
  </programme><programme channel="9-Mystery-and-Paranormal-AU" start="20260504123428 +0500" stop="20260504133428 +0500">
    <title>Mystery &amp; Paranormal Show</title>
    <desc>9Mystery &amp; Paranormal provides supernatural documentaries, unexplained phenomena, and mystery-focused entertainment programming.</desc>
    <category>Mystery</category>
    <language>en</language>
  </programme><programme channel="9-Mystery-and-Paranormal-AU" start="20260504133428 +0500" stop="20260504143428 +0500">
    <title>Mystery &amp; Paranormal Show</title>
    <desc>9Mystery &amp; Paranormal provides supernatural documentaries, unexplained phenomena, and mystery-focused entertainment programming.</desc>
    <category>Mystery</category>
    <language>en</language>
  </programme><programme channel="9-Mystery-and-Paranormal-AU" start="20260504143428 +0500" stop="20260504153428 +0500">
    <title>Mystery &amp; Paranormal Show</title>
    <desc>9Mystery &amp; Paranormal provides supernatural documentaries, unexplained phenomena, and mystery-focused entertainment programming.</desc>
    <category>Mystery</category>
    <language>en</language>
  </programme><programme channel="9-Mystery-and-Paranormal-AU" start="20260504153428 +0500" stop="20260504163428 +0500">
    <title>Mystery &amp; Paranormal Show</title>
    <desc>9Mystery &amp; Paranormal provides supernatural documentaries, unexplained phenomena, and mystery-focused entertainment programming.</desc>
    <category>Mystery</category>
    <language>en</language>
  </programme><programme channel="9-Mystery-and-Paranormal-AU" start="20260504163428 +0500" stop="20260504173428 +0500">
    <title>Mystery &amp; Paranormal Show</title>
    <desc>9Mystery &amp; Paranormal provides supernatural documentaries, unexplained phenomena, and mystery-focused entertainment programming.</desc>
    <category>Mystery</category>
    <language>en</language>
  </programme><programme channel="9-Mystery-and-Paranormal-AU" start="20260504173428 +0500" stop="20260504183428 +0500">
    <title>Mystery &amp; Paranormal Show</title>
    <desc>9Mystery &amp; Paranormal provides supernatural documentaries, unexplained phenomena, and mystery-focused entertainment programming.</desc>
    <category>Mystery</category>
    <language>en</language>
  </programme><programme channel="9-Mystery-and-Paranormal-AU" start="20260504183428 +0500" stop="20260504193428 +0500">
    <title>Mystery &amp; Paranormal Show</title>
    <desc>9Mystery &amp; Paranormal provides supernatural documentaries, unexplained phenomena, and mystery-focused entertainment programming.</desc>
    <category>Mystery</category>
    <language>en</language>
  </programme><programme channel="9-Mystery-and-Paranormal-AU" start="20260504193428 +0500" stop="20260504203428 +0500">
    <title>Mystery &amp; Paranormal Show</title>
    <desc>9Mystery &amp; Paranormal provides supernatural documentaries, unexplained phenomena, and mystery-focused entertainment programming.</desc>
    <category>Mystery</category>
    <language>en</language>
  </programme><programme channel="9-Mystery-and-Paranormal-AU" start="20260504203428 +0500" stop="20260504213428 +0500">
    <title>Mystery &amp; Paranormal Show</title>
    <desc>9Mystery &amp; Paranormal provides supernatural documentaries, unexplained phenomena, and mystery-focused entertainment programming.</desc>
    <category>Mystery</category>
    <language>en</language>
  </programme><programme channel="9-Mystery-and-Paranormal-AU" start="20260504213428 +0500" stop="20260504223428 +0500">
    <title>Mystery &amp; Paranormal Show</title>
    <desc>9Mystery &amp; Paranormal provides supernatural documentaries, unexplained phenomena, and mystery-focused entertainment programming.</desc>
    <category>Mystery</category>
    <language>en</language>
  </programme><programme channel="9-Mystery-and-Paranormal-AU" start="20260504223428 +0500" stop="20260504233428 +0500">
    <title>Mystery &amp; Paranormal Show</title>
    <desc>9Mystery &amp; Paranormal provides supernatural documentaries, unexplained phenomena, and mystery-focused entertainment programming.</desc>
    <category>Mystery</category>
    <language>en</language>
  </programme><programme channel="9-Mystery-and-Paranormal-AU" start="20260504233428 +0500" stop="20260504235959 +0500">
    <title>Mystery &amp; Paranormal Show</title>
    <desc>9Mystery &amp; Paranormal provides supernatural documentaries, unexplained phenomena, and mystery-focused entertainment programming.</desc>
    <category>Mystery</category>
    <language>en</language>
  </programme>
</tv>